sentence_concreteness/__init__.py
sentence_concreteness/sentence_concreteness.py
sentence_concreteness-0.0.1.dist-info/LICENSE
sentence_concreteness-0.0.1.dist-info/METADATA
sentence_concreteness-0.0.1.dist-info/WHEEL
sentence_concreteness-0.0.1.dist-info/top_level.txt
sentence_concreteness-0.0.1.dist-info/RECORD
