Metadata-Version: 2.1
Name: sentence-concreteness
Version: 0.0.1
Summary: A function to tag sentences with a validated measure of sentence concreteness
Home-page: https://github.com/maubinle/sentence_concreteness.git
Author: Marianne Aubin Le Quere
Author-email: msa258@cornell.edu
License: MIT
Classifier: Programming Language :: Python :: 3
Classifier: Operating System :: OS Independent
Requires-Python: >=3.7
License-File: LICENSE
Requires-Dist: truecase
Requires-Dist: string
Requires-Dist: typing-extensions ==4.4.0
Requires-Dist: inflect
Requires-Dist: nltk
Requires-Dist: numpy ==1.21.0
Requires-Dist: spacy ==3.2.0
Provides-Extra: spacy_models
Requires-Dist: en-core-web-sm ; extra == 'spacy_models'
